[
  {
    "id": 1,
    "email": "george.bluth@reqres.in",
    "first_name": "George",
    "last_name": "Bluth",
    "avatar": "https://reqres.in/img/faces/1-image.jpg"
  },
  {
    "id": 2,
    "email": "janet.weaver@reqres.in",
    "first_name": "Janet",
    "last_name": "Weaver",
    "avatar": "https://reqres.in/img/faces/2-image.jpg"
  },
  {
    "id": 3,
    "email": "emma.wong@reqres.in",
    "first_name": "Emma",
    "last_name": "Wong",
    "avatar": "https://reqres.in/img/faces/3-image.jpg"
  },
  {
    "id": 4,
    "email": "eve.holt@reqres.in",
    "first_name": "Eve",
    "last_name": "Holt",
    "avatar": "https://reqres.in/img/faces/4-image.jpg"
  },
  {
    "id": 5,
    "email": "charles.morris@reqres.in",
    "first_name": "Charles",
    "last_name": "Morris",
    "avatar": "https://reqres.in/img/faces/5-image.jpg"
  },
  {
    "id": 6,
    "email": "tracey.ramos@reqres.in",
    "first_name": "Tracey",
    "last_name": "Ramos",
    "avatar": "https://reqres.in/img/faces/6-image.jpg"
  },
  {
    "id": 6,
    "email": "ucup@Mail.com",
    "first_name": "Muhammad",
    "last_name": "Yusuf",
    "avatar": "https://cdn.pixabay.com/photo/2018/08/28/12/41/avatar-3637425_960_720.png"
  },
  {
    "id": 7,
    "email": "mm@gmail.com",
    "first_name": "malwer",
    "last_name": "mahmud",
    "avatar": "https://i.pinimg.com/originals/71/b1/62/71b162e0e34438b4ccc959da1ac12ae0.jpg"
  },
  {
    "id": 8,
    "email": "hd@gmail.com",
    "first_name": "hafid",
    "last_name": "durohman",
    "avatar": "https://www.google.com/url?sa=i&url=https%3A%2F%2Fshopee.co.id%2F(Baru!!)-Mewarnai-Gambar-Gambar-Mewarnai-Anak-Kertas-Gambar-30-lembar-i.51801868.4238375506&psig=AOvVaw0Bzt7TJVhy38EP-BhnhyAX&ust=1632243062458000&source=images&cd=vfe&ved=0CAsQjRxqFwoTCLDHhbOBjvMCFQAAAAAdAAAAABAD"
  }
]